pybujia/__init__.py
pybujia/fixtures.py
pybujia/helpers.py
pybujia/py.typed
pybujia-0.1.0rc9.dist-info/licenses/LICENSE
pybujia-0.1.0rc9.dist-info/METADATA
pybujia-0.1.0rc9.dist-info/WHEEL
pybujia-0.1.0rc9.dist-info/top_level.txt
pybujia-0.1.0rc9.dist-info/RECORD
