Metadata-Version: 2.4
Name: pybujia
Version: 0.1.0rc9
Summary: Enables human-readable formats like Markdown or Spark's .show() for unit test input/expected tables — easy to document and version, making test data changes simple to track and review
Author-email: Juan Pablo Guereca <juanpablo@guereca.com>
License-Expression: MIT
Project-URL: Repository, https://github.com/jpgerek/pybujia
Keywords: pyspark,fixtures,tests,readable
Classifier: Operating System :: OS Independent
Classifier: Programming Language :: Python
Classifier: Programming Language :: Python :: 3
Classifier: Programming Language :: Python :: 3.9
Classifier: Programming Language :: Python :: 3.10
Classifier: Programming Language :: Python :: 3.11
Classifier: Programming Language :: Python :: 3.12
Classifier: Topic :: Software Development :: Testing
Requires-Python: >=3.9
License-File: LICENSE
Requires-Dist: pyspark>=3.0.0
Provides-Extra: dev
Requires-Dist: black==25.1.0; extra == "dev"
Requires-Dist: mypy==1.15.0; extra == "dev"
Requires-Dist: pre-commit==3.7.1; extra == "dev"
Requires-Dist: pyright==1.1.399; extra == "dev"
Requires-Dist: pytest==8.2.2; extra == "dev"
Requires-Dist: pytest-cov==6.1.1; extra == "dev"
Requires-Dist: ruff==0.6.3; extra == "dev"
Dynamic: license-file
